semverbump/__init__.py
semverbump/bump.py
semverbump-0.2.2.dist-info/LICENSE
semverbump-0.2.2.dist-info/METADATA
semverbump-0.2.2.dist-info/WHEEL
semverbump-0.2.2.dist-info/entry_points.txt
semverbump-0.2.2.dist-info/RECORD
