Metadata-Version: 2.1
Name: semverbump
Version: 0.2.2
Summary: A CLI tool that auto-bumps version number for your app.
License: MIT
Author: Nikhil Akki
Author-email: 17634231+nikhilakki@users.noreply.github.com
Requires-Python: >=3.9,<4.0
Classifier: License :: OSI Approved :: MIT License
Classifier: Programming Language :: Python :: 3
Classifier: Programming Language :: Python :: 3.9
Classifier: Programming Language :: Python :: 3.10
Classifier: Programming Language :: Python :: 3.11
